{
    "indexes": [
        {
            "collectionGroup": "appointments",
            "queryScope": "COLLECTION",
            "fields": [
                {
                    "fieldPath": "doctorId",
                    "order": "ASCENDING"
                },
                {
                    "fieldPath": "status",
                    "order": "ASCENDING"
                }
            ]
        },
        {
            "collectionGroup": "appointments",
            "queryScope": "COLLECTION",
            "fields": [
                {
                    "fieldPath": "patientId",
                    "order": "ASCENDING"
                },
                {
                    "fieldPath": "status",
                    "order": "ASCENDING"
                }
            ]
        },
        {
            "collectionGroup": "appointments",
            "queryScope": "COLLECTION",
            "fields": [
                {
                    "fieldPath": "doctorId",
                    "order": "ASCENDING"
                },
                {
                    "fieldPath": "createdAt",
                    "order": "DESCENDING"
                }
            ]
        },
        {
            "collectionGroup": "appointments",
            "queryScope": "COLLECTION",
            "fields": [
                {
                    "fieldPath": "patientId",
                    "order": "ASCENDING"
                },
                {
                    "fieldPath": "createdAt",
                    "order": "DESCENDING"
                }
            ]
        },
        {
            "collectionGroup": "chats",
            "queryScope": "COLLECTION",
            "fields": [
                {
                    "fieldPath": "participants",
                    "arrayConfig": "CONTAINS"
                },
                {
                    "fieldPath": "updatedAt",
                    "order": "DESCENDING"
                }
            ]
        },
        {
            "collectionGroup": "messages",
            "queryScope": "COLLECTION",
            "fields": [
                {
                    "fieldPath": "chatId",
                    "order": "ASCENDING"
                },
                {
                    "fieldPath": "timestamp",
                    "order": "ASCENDING"
                }
            ]
        },
        {
            "collectionGroup": "prescriptions",
            "queryScope": "COLLECTION",
            "fields": [
                {
                    "fieldPath": "patientId",
                    "order": "ASCENDING"
                },
                {
                    "fieldPath": "createdAt",
                    "order": "DESCENDING"
                }
            ]
        },
        {
            "collectionGroup": "labs",
            "queryScope": "COLLECTION",
            "fields": [
                {
                    "fieldPath": "patientId",
                    "order": "ASCENDING"
                },
                {
                    "fieldPath": "createdAt",
                    "order": "DESCENDING"
                }
            ]
        },
        {
            "collectionGroup": "visits",
            "queryScope": "COLLECTION",
            "fields": [
                {
                    "fieldPath": "patientId",
                    "order": "ASCENDING"
                },
                {
                    "fieldPath": "createdAt",
                    "order": "DESCENDING"
                }
            ]
        }
    ],
    "fieldOverrides": []
}